azure/__init__.py
azure/cli/__init__.py
azure/cli/command_modules/__init__.py
azure/cli/command_modules/batchai/__init__.py
azure/cli/command_modules/batchai/_client_factory.py
azure/cli/command_modules/batchai/_format.py
azure/cli/command_modules/batchai/_help.py
azure/cli/command_modules/batchai/_params.py
azure/cli/command_modules/batchai/commands.py
azure/cli/command_modules/batchai/custom.py
azure_cli_batchai-0.4.10.dist-info/METADATA
azure_cli_batchai-0.4.10.dist-info/WHEEL
azure_cli_batchai-0.4.10.dist-info/top_level.txt
azure_cli_batchai-0.4.10.dist-info/RECORD
