Metadata-Version: 2.1
Name: azure-cli-batchai
Version: 0.4.10
Summary: Microsoft Azure Batch AI Client Command-Line Tools
Home-page: https://github.com/Azure/azure-cli
Author: Microsoft Corporation
Author-email: ayukha@microsoft.com
License: MIT
Platform: UNKNOWN
Classifier: Development Status :: 4 - Beta
Classifier: Intended Audience :: Developers
Classifier: Intended Audience :: System Administrators
Classifier: Programming Language :: Python
Classifier: Programming Language :: Python :: 2
Classifier: Programming Language :: Python :: 2.7
Classifier: Programming Language :: Python :: 3
Classifier: Programming Language :: Python :: 3.4
Classifier: Programming Language :: Python :: 3.5
Classifier: Programming Language :: Python :: 3.6
Classifier: License :: OSI Approved :: MIT License
Requires-Dist: azure-mgmt-storage (==3.3.0)
Requires-Dist: azure-mgmt-batchai (==2.0.0)
Requires-Dist: azure-storage-blob (==1.3.1)
Requires-Dist: azure-cli-core
Requires-Dist: mock (>=2.0.0)
Requires-Dist: sshtunnel
Requires-Dist: azure-cli-command-modules-nspkg (>=2.0.0)
